lifespring/__init__.py
lifespring/bucket_tools.py
lifespring/eventsourcing.py
lifespring/lifespring.py
lifespring/locales/en_US/LC_MESSAGES/messages.mo
lifespring/locales/zh_CN/LC_MESSAGES/messages.mo
lifespring/miscellaneous/__init__.py
lifespring/miscellaneous/hello.py
lifespring/utils/__init__.py
lifespring/utils/functional/__init__.py
lifespring/utils/functional/lifespring_types.py
lifespring/utils/functional/transfer_funcs.py
lifespring/utils/fundamental/__init__.py
lifespring/utils/fundamental/external.py
lifespring/utils/fundamental/i18n.py
lifespring/utils/fundamental/json_tools.py
lifespring/utils/fundamental/pywheels.py
lifespring/utils/fundamental/time.py
lifespring/utils/fundamental/typing.py
lifespring-0.0.1.4.dist-info/METADATA
lifespring-0.0.1.4.dist-info/WHEEL
lifespring-0.0.1.4.dist-info/top_level.txt
lifespring-0.0.1.4.dist-info/RECORD
